jconfigparser/__init__.py
jconfigparser/core.py
jconfigparser/dict.py
jconfigparser-0.1.3.dist-info/LICENSE
jconfigparser-0.1.3.dist-info/WHEEL
jconfigparser-0.1.3.dist-info/METADATA
jconfigparser-0.1.3.dist-info/RECORD
